{
  "0": [],
  "1": [
    26
  ],
  "2": [],
  "3": [],
  "4": [
    93
  ],
  "5": [
    130
  ],
  "6": [
    132
  ],
  "7": [],
  "8": [],
  "9": [],
  "10": [
    142
  ],
  "11": [
    144
  ],
  "12": [
    146
  ],
  "13": [],
  "14": [],
  "15": [],
  "16": [
    30
  ],
  "17": [
    135
  ],
  "18": [
    138
  ],
  "19": [
    140
  ],
  "20": [
    330
  ],
  "21": [
    392
  ],
  "22": [
    417
  ],
  "23": [
    418
  ],
  "24": [
    419
  ],
  "25": [
    420
  ],
  "26": [
    421
  ],
  "27": [
    479
  ],
  "28": [],
  "29": [
    587
  ],
  "30": [
    592
  ],
  "31": [
    595
  ],
  "32": [
    605
  ],
  "33": [
    606
  ],
  "34": [
    608
  ],
  "35": [
    610
  ],
  "36": [
    615
  ],
  "37": [
    616
  ],
  "38": [
    617
  ],
  "39": [
    618
  ],
  "40": [],
  "41": [
    622
  ],
  "42": [
    623
  ],
  "43": [
    624
  ],
  "44": [
    663
  ],
  "45": [
    720
  ],
  "46": [
    721
  ],
  "47": [
    722
  ],
  "48": [],
  "49": [],
  "50": [],
  "51": [],
  "52": [],
  "53": [],
  "54": [],
  "55": [],
  "56": [],
  "57": [],
  "58": [],
  "59": [],
  "60": [
    3584
  ],
  "61": [],
  "62": [],
  "63": [],
  "64": [],
  "65": [],
  "66": [
    745
  ],
  "67": [
    746
  ],
  "68": [
    747
  ],
  "69": [],
  "70": [],
  "71": [],
  "72": [
    750
  ],
  "73": [
    752
  ],
  "74": [
    764
  ],
  "75": [
    768
  ],
  "76": [
    769
  ],
  "77": [
    770
  ],
  "78": [
    1723
  ],
  "79": [],
  "80": [],
  "81": [],
  "82": [
    825
  ],
  "83": [],
  "84": [
    884
  ],
  "85": [
    927
  ],
  "86": [],
  "87": [],
  "88": [
    1267
  ],
  "89": [
    1268
  ],
  "90": [
    1269
  ],
  "91": [
    1270
  ],
  "92": [
    1271
  ],
  "93": [
    1272
  ],
  "94": [],
  "95": [],
  "96": [],
  "97": [],
  "98": [],
  "99": [],
  "100": [
    1378
  ],
  "101": [
    1379
  ],
  "102": [
    1380
  ],
  "103": [
    1381
  ],
  "104": [
    1382
  ],
  "105": [
    1383
  ],
  "106": [
    1447
  ],
  "107": [
    1448
  ],
  "108": [
    1126
  ],
  "109": [
    1590
  ],
  "110": [
    1592
  ],
  "111": [
    1594
  ],
  "112": [
    1102
  ],
  "113": [
    1726
  ],
  "114": [
    1728
  ],
  "115": [
    1730
  ],
  "116": [
    1948
  ],
  "117": [
    1949
  ],
  "118": [
    1950
  ],
  "119": [
    1951
  ],
  "120": [
    1952
  ],
  "121": [
    1953
  ],
  "122": [
    1954
  ],
  "123": [
    1955
  ],
  "124": [
    1956
  ],
  "125": [
    1957
  ],
  "126": [
    2008
  ],
  "127": [
    2009
  ],
  "128": [
    2010
  ],
  "129": [
    2011
  ],
  "130": [
    2012
  ],
  "131": [
    2013
  ],
  "132": [
    2014
  ],
  "133": [
    2158
  ],
  "134": [
    2159
  ],
  "135": [
    2160
  ],
  "136": [
    2169
  ],
  "137": [
    2170
  ],
  "138": [
    2210
  ],
  "139": [
    2211
  ],
  "140": [
    2212
  ],
  "141": [
    2213
  ],
  "142": [
    2263
  ],
  "143": [
    2264
  ],
  "144": [
    2271
  ],
  "145": [
    2333
  ],
  "146": [
    2432
  ],
  "147": [
    2433
  ],
  "148": [
    2434
  ],
  "149": [
    2505
  ],
  "150": [
    2507
  ],
  "151": [
    2506
  ],
  "152": [
    2508
  ],
  "153": [
    2677
  ],
  "154": [
    2679
  ],
  "155": [
    2681
  ],
  "156": [
    2683
  ],
  "157": [
    2678
  ],
  "158": [
    2680
  ],
  "159": [
    2682
  ],
  "160": [
    2684
  ],
  "161": [
    2686
  ],
  "162": [
    2688
  ],
  "163": [
    2690
  ],
  "164": [
    2685
  ],
  "165": [
    2687
  ],
  "166": [
    2689
  ],
  "167": [
    2691
  ],
  "168": [
    2696
  ],
  "169": [
    2698
  ],
  "170": [],
  "171": [],
  "172": [
    2788
  ],
  "173": [
    2789
  ],
  "174": [
    2790
  ],
  "175": [
    2791
  ],
  "176": [
    2861
  ],
  "177": [
    3067
  ],
  "178": [],
  "179": [
    3083
  ],
  "180": [],
  "181": [
    3089
  ],
  "182": [
    3101
  ],
  "183": [
    3082
  ],
  "184": [
    3088
  ],
  "185": [],
  "186": [
    3238
  ],
  "187": [],
  "188": [],
  "189": [],
  "190": [],
  "191": [],
  "192": [],
  "193": [],
  "194": [],
  "195": [],
  "196": [],
  "197": [],
  "198": [],
  "199": [],
  "200": [],
  "201": [],
  "202": [],
  "203": [],
  "204": [],
  "205": [],
  "206": [],
  "207": [],
  "208": [],
  "209": [],
  "210": [],
  "211": [],
  "212": [],
  "213": [],
  "214": [],
  "215": [],
  "216": [],
  "217": [],
  "218": [],
  "219": [],
  "220": [],
  "221": [],
  "222": [],
  "223": [],
  "224": [
    3472
  ],
  "225": [
    3751
  ],
  "226": [
    3752
  ],
  "227": [
    3753
  ],
  "228": [
    3760
  ],
  "229": [
    3761
  ],
  "230": [
    3762
  ],
  "231": [
    3952
  ],
  "232": [
    3954
  ],
  "233": [
    3956
  ],
  "234": [
    4052
  ],
  "235": [
    4053
  ],
  "236": [
    4140
  ],
  "237": [
    4233
  ],
  "238": [
    4234
  ],
  "239": [
    4235
  ],
  "240": [
    4236
  ],
  "241": [
    4260
  ],
  "242": [
    4279
  ],
  "243": [
    4280
  ],
  "244": [],
  "245": [
    4424
  ],
  "246": [
    4486
  ],
  "247": [
    4487
  ],
  "248": [
    4488
  ],
  "249": [
    4489
  ],
  "250": [
    4490
  ],
  "251": [
    4491
  ],
  "252": [
    4492
  ],
  "253": [
    4493
  ],
  "254": [
    4494
  ],
  "255": [
    4495
  ],
  "256": [
    4496
  ],
  "257": [
    4497
  ],
  "258": [
    4498
  ],
  "259": [
    4499
  ],
  "260": [
    4500
  ],
  "261": [
    4501
  ],
  "262": [
    4502
  ],
  "263": [
    4503
  ],
  "264": [
    4504
  ],
  "265": [
    4505
  ],
  "266": [
    4506
  ],
  "267": [
    4507
  ],
  "268": [
    4508
  ],
  "269": [
    4509
  ],
  "270": [
    4510
  ],
  "271": [
    4511
  ],
  "272": [],
  "273": [],
  "274": [
    4512
  ],
  "275": [
    3273
  ],
  "276": [
    4513
  ],
  "277": [
    4514
  ],
  "278": [
    4515
  ],
  "279": [
    4516
  ],
  "280": [
    4517
  ],
  "281": [
    4518
  ],
  "282": [
    4519
  ],
  "283": [
    4520
  ],
  "284": [
    4521
  ],
  "285": [
    4522
  ],
  "286": [
    4523
  ],
  "287": [
    4524
  ],
  "288": [
    4525
  ],
  "289": [
    4526
  ],
  "290": [
    4527
  ],
  "291": [
    4528
  ],
  "292": [
    4529
  ],
  "293": [
    4530
  ],
  "294": [
    4531
  ],
  "295": [
    4532
  ],
  "296": [
    4533
  ],
  "297": [
    4534
  ],
  "298": [
    4535
  ],
  "299": [
    4536
  ],
  "300": [
    4537
  ],
  "301": [
    4538
  ],
  "302": [
    4539
  ],
  "303": [
    4540
  ],
  "304": [
    3340
  ],
  "305": [
    3341
  ],
  "306": [
    3342
  ],
  "307": [
    3343
  ],
  "308": [
    3344
  ],
  "309": [
    3345
  ],
  "310": [
    3346
  ],
  "311": [
    3348
  ],
  "312": [
    4565
  ],
  "313": [
    4548
  ],
  "314": [
    4647
  ],
  "315": [
    4667
  ],
  "316": []
}